{
    "scoringGroup": {
        "format": "team",
        "captionLong": "Male/Male Masters 45+",
        "order": 6,
        "gender": null,
        "divisionId": 64683,
        "team": true,
        "displayNation": false,
        "scoringMethod": "rank",
        "overallTiebreakerOption": "",
        "overallTiebreakerWorkoutId": null,
        "divisionAdvancingNumbers": null,
        "name": "team_64683",
        "caption": "Male/Male Masters 45+"
    },
    "isMultiLeaderboard": false,
    "isPointSeries": false,
    "scoringGroupName": "team_64683",
    "headerLabel": "Points",
    "displayNation": false,
    "showTotal": true,
    "showDeficitPoints": false,
    "useCustomFieldsAsFilter": false,
    "workouts": [
        {
            "id": 65445,
            "key": "workout_65445",
            "name": "Hoppin' and Poppin'!",
            "logoPath": "",
            "showDetails": true,
            "showPoints": true,
            "hasMissingScores": false,
            "caption": "Time",
            "showRank": false,
            "headerLabel": "Points",
            "scoresCount": 4,
            "hasResultsOperations": false,
            "hasActiveResultsOperations": false,
            "resultsOperationsEndDate": null,
            "resultsOperationsNextStartDate": null
        },
        {
            "id": 65574,
            "key": "workout_65574",
            "name": "3-1-2? It's So Complex!",
            "logoPath": "",
            "showDetails": true,
            "showPoints": true,
            "hasMissingScores": false,
            "caption": "lb",
            "showRank": false,
            "headerLabel": "Points",
            "scoresCount": 4,
            "hasResultsOperations": false,
            "hasActiveResultsOperations": false,
            "resultsOperationsEndDate": null,
            "resultsOperationsNextStartDate": null
        },
        {
            "id": 65703,
            "key": "workout_65703",
            "name": "Toss it, I'm Over It! (Row)",
            "logoPath": "",
            "showDetails": true,
            "showPoints": true,
            "hasMissingScores": false,
            "caption": "Calories",
            "showRank": false,
            "headerLabel": "Points",
            "scoresCount": 4,
            "hasResultsOperations": false,
            "hasActiveResultsOperations": false,
            "resultsOperationsEndDate": null,
            "resultsOperationsNextStartDate": null
        },
        {
            "id": 65832,
            "key": "workout_65832",
            "name": "Toss it, I'm Over It! (Metcon)",
            "logoPath": "",
            "showDetails": true,
            "showPoints": true,
            "hasMissingScores": false,
            "caption": "Reps",
            "showRank": false,
            "headerLabel": "Points",
            "scoresCount": 4,
            "hasResultsOperations": false,
            "hasActiveResultsOperations": false,
            "resultsOperationsEndDate": null,
            "resultsOperationsNextStartDate": null
        },
        {
            "id": 65961,
            "key": "workout_65961",
            "name": "Get on Up 'n Git Down",
            "logoPath": "",
            "showDetails": true,
            "showPoints": true,
            "hasMissingScores": false,
            "caption": "Time",
            "showRank": false,
            "headerLabel": "Points",
            "scoresCount": 4,
            "hasResultsOperations": false,
            "hasActiveResultsOperations": false,
            "resultsOperationsEndDate": null,
            "resultsOperationsNextStartDate": null
        }
    ],
    "athletes": [
        {
            "name": "NXTLVL MASTERS ",
            "avatarPath": null,
            "place": "1",
            "totalPoints": "9",
            "deficit": null,
            "totalWins": "2",
            "topFiveFinishes": "5",
            "subgroup": null,
            "subcategory": null,
            "events": null,
            "affiliate": "NXTLVL SPORT AND FITNESS",
            "ptcpID": "926448",
            "rosterID": "484973",
            "wd": false,
            "dnf": false,
            "pending": false,
            "isDisqualified": false,
            "submittedScores": 5,
            "specialStatus": null,
            "nextScaled": false,
            "workoutScores": {
                "workout_65445": {
                    "workoutId": 65445,
                    "points": "1",
                    "rank": "",
                    "res": "04:20",
                    "cssNames": "",
                    "nonOff": false,
                    "caption": "Time",
                    "rankInnerValue": 1,
                    "hasHiddenResult": false,
                    "hasVideo": false
                },
                "workout_65574": {
                    "workoutId": 65574,
                    "points": "1",
                    "rank": "",
                    "res": "500",
                    "cssNames": "",
                    "nonOff": false,
                    "caption": "Weight (lb)",
                    "rankInnerValue": 1,
                    "hasHiddenResult": false,
                    "hasVideo": false
                },
                "workout_65703": {
                    "workoutId": 65703,
                    "points": "2",
                    "rank": "",
                    "res": "188",
                    "cssNames": "",
                    "nonOff": false,
                    "caption": "Calories",
                    "rankInnerValue": 2,
                    "hasHiddenResult": false,
                    "hasVideo": false
                },
                "workout_65832": {
                    "workoutId": 65832,
                    "points": "3",
                    "rank": "",
                    "res": "300",
                    "cssNames": "",
                    "nonOff": false,
                    "caption": "Reps",
                    "rankInnerValue": 3,
                    "hasHiddenResult": false,
                    "hasVideo": false
                },
                "workout_65961": {
                    "workoutId": 65961,
                    "points": "2",
                    "rank": "",
                    "res": "05:13",
                    "cssNames": "",
                    "nonOff": false,
                    "caption": "Time",
                    "rankInnerValue": 2,
                    "hasHiddenResult": false,
                    "hasVideo": false
                }
            },
            "countryName": "United States",
            "countryCode": "USA",
            "countryShortCode": "US",
            "index": 0,
            "ageGroup": null,
            "combinedTeamAge": 94,
            "bibNumber": null,
            "participantAnswers": null,
            "infoOptionCustomFieldValue": null
        },
        {
            "name": "The Grim Bastards",
            "avatarPath": null,
            "place": "2",
            "totalPoints": "10",
            "deficit": null,
            "totalWins": "2",
            "topFiveFinishes": "5",
            "subgroup": null,
            "subcategory": null,
            "events": null,
            "affiliate": "BAMFIT ATHLETICS",
            "ptcpID": "881053",
            "rosterID": "467760",
            "wd": false,
            "dnf": false,
            "pending": false,
            "isDisqualified": false,
            "submittedScores": 5,
            "specialStatus": null,
            "nextScaled": false,
            "workoutScores": {
                "workout_65445": {
                    "workoutId": 65445,
                    "points": "2",
                    "rank": "",
                    "res": "04:51",
                    "cssNames": "",
                    "nonOff": false,
                    "caption": "Time",
                    "rankInnerValue": 2,
                    "hasHiddenResult": false,
                    "hasVideo": false
                },
                "workout_65574": {
                    "workoutId": 65574,
                    "points": "3",
                    "rank": "",
                    "res": "400",
                    "cssNames": "",
                    "nonOff": false,
                    "caption": "Weight (lb)",
                    "rankInnerValue": 3,
                    "hasHiddenResult": false,
                    "hasVideo": false
                },
                "workout_65703": {
                    "workoutId": 65703,
                    "points": "3",
                    "rank": "",
                    "res": "166",
                    "cssNames": "",
                    "nonOff": false,
                    "caption": "Calories",
                    "rankInnerValue": 3,
                    "hasHiddenResult": false,
                    "hasVideo": false
                },
                "workout_65832": {
                    "workoutId": 65832,
                    "points": "1",
                    "rank": "",
                    "res": "315",
                    "cssNames": "",
                    "nonOff": false,
                    "caption": "Reps",
                    "rankInnerValue": 1,
                    "hasHiddenResult": false,
                    "hasVideo": false
                },
                "workout_65961": {
                    "workoutId": 65961,
                    "points": "1",
                    "rank": "",
                    "res": "04:55",
                    "cssNames": "",
                    "nonOff": false,
                    "caption": "Time",
                    "rankInnerValue": 1,
                    "hasHiddenResult": false,
                    "hasVideo": false
                }
            },
            "countryName": "United States",
            "countryCode": "USA",
            "countryShortCode": "US",
            "index": 1,
            "ageGroup": null,
            "combinedTeamAge": 92,
            "bibNumber": null,
            "participantAnswers": null,
            "infoOptionCustomFieldValue": null
        },
        {
            "name": "CF Lumberyard Used 2 Coulds",
            "avatarPath": null,
            "place": "3",
            "totalPoints": "11",
            "deficit": null,
            "totalWins": "1",
            "topFiveFinishes": "5",
            "subgroup": null,
            "subcategory": null,
            "events": null,
            "affiliate": "CROSSFIT LUMBERYARD",
            "ptcpID": "912711",
            "rosterID": "485876",
            "wd": false,
            "dnf": false,
            "pending": false,
            "isDisqualified": false,
            "submittedScores": 5,
            "specialStatus": null,
            "nextScaled": false,
            "workoutScores": {
                "workout_65445": {
                    "workoutId": 65445,
                    "points": "3",
                    "rank": "",
                    "res": "05:27",
                    "cssNames": "",
                    "nonOff": false,
                    "caption": "Time",
                    "rankInnerValue": 3,
                    "hasHiddenResult": false,
                    "hasVideo": false
                },
                "workout_65574": {
                    "workoutId": 65574,
                    "points": "2",
                    "rank": "",
                    "res": "440",
                    "cssNames": "",
                    "nonOff": false,
                    "caption": "Weight (lb)",
                    "rankInnerValue": 2,
                    "hasHiddenResult": false,
                    "hasVideo": false
                },
                "workout_65703": {
                    "workoutId": 65703,
                    "points": "1",
                    "rank": "",
                    "res": "211",
                    "cssNames": "",
                    "nonOff": false,
                    "caption": "Calories",
                    "rankInnerValue": 1,
                    "hasHiddenResult": false,
                    "hasVideo": false
                },
                "workout_65832": {
                    "workoutId": 65832,
                    "points": "2",
                    "rank": "",
                    "res": "312",
                    "cssNames": "",
                    "nonOff": false,
                    "caption": "Reps",
                    "rankInnerValue": 2,
                    "hasHiddenResult": false,
                    "hasVideo": false
                },
                "workout_65961": {
                    "workoutId": 65961,
                    "points": "3",
                    "rank": "",
                    "res": "05:41",
                    "cssNames": "",
                    "nonOff": false,
                    "caption": "Time",
                    "rankInnerValue": 3,
                    "hasHiddenResult": false,
                    "hasVideo": false
                }
            },
            "countryName": "United States",
            "countryCode": "USA",
            "countryShortCode": "US",
            "index": 2,
            "ageGroup": null,
            "combinedTeamAge": 112,
            "bibNumber": null,
            "participantAnswers": null,
            "infoOptionCustomFieldValue": null
        },
        {
            "name": "The Diddly Squats",
            "avatarPath": null,
            "place": "4",
            "totalPoints": "20",
            "deficit": null,
            "totalWins": "0",
            "topFiveFinishes": "5",
            "subgroup": null,
            "subcategory": null,
            "events": null,
            "affiliate": "CROSSFIT RECOIL",
            "ptcpID": "922863",
            "rosterID": "483438",
            "wd": false,
            "dnf": false,
            "pending": false,
            "isDisqualified": false,
            "submittedScores": 5,
            "specialStatus": null,
            "nextScaled": false,
            "workoutScores": {
                "workout_65445": {
                    "workoutId": 65445,
                    "points": "4",
                    "rank": "",
                    "res": "05:36",
                    "cssNames": "",
                    "nonOff": false,
                    "caption": "Time",
                    "rankInnerValue": 4,
                    "hasHiddenResult": false,
                    "hasVideo": false
                },
                "workout_65574": {
                    "workoutId": 65574,
                    "points": "4",
                    "rank": "",
                    "res": "285",
                    "cssNames": "",
                    "nonOff": false,
                    "caption": "Weight (lb)",
                    "rankInnerValue": 4,
                    "hasHiddenResult": false,
                    "hasVideo": false
                },
                "workout_65703": {
                    "workoutId": 65703,
                    "points": "4",
                    "rank": "",
                    "res": "136",
                    "cssNames": "",
                    "nonOff": false,
                    "caption": "Calories",
                    "rankInnerValue": 4,
                    "hasHiddenResult": false,
                    "hasVideo": false
                },
                "workout_65832": {
                    "workoutId": 65832,
                    "points": "4",
                    "rank": "",
                    "res": "272",
                    "cssNames": "",
                    "nonOff": false,
                    "caption": "Reps",
                    "rankInnerValue": 4,
                    "hasHiddenResult": false,
                    "hasVideo": false
                },
                "workout_65961": {
                    "workoutId": 65961,
                    "points": "4",
                    "rank": "",
                    "res": "06:21",
                    "cssNames": "",
                    "nonOff": false,
                    "caption": "Time",
                    "rankInnerValue": 4,
                    "hasHiddenResult": false,
                    "hasVideo": false
                }
            },
            "countryName": "United States",
            "countryCode": "USA",
            "countryShortCode": "US",
            "index": 3,
            "ageGroup": null,
            "combinedTeamAge": 90,
            "bibNumber": null,
            "participantAnswers": null,
            "infoOptionCustomFieldValue": null
        }
    ],
    "affiliateFilterValues": [],
    "countryFilterValues": [],
    "ageGroupsFilterValues": null,
    "subGroupFilterValues": null,
    "customFieldsFilterValues": null,
    "continentFilterValues": null,
    "regionFilterValues": null,
    "showGenderFilterValues": false,
    "hasAthletes": true
}