{"scoringGroup":{"format":"team","captionLong":"Female/Male Intermediate","order":5,"gender":null,"divisionId":64697,"team":true,"displayNation":false,"scoringMethod":"rank","overallTiebreakerOption":"","overallTiebreakerWorkoutId":null,"divisionAdvancingNumbers":null,"name":"team_64697","caption":"Female/Male Intermediate"},"isMultiLeaderboard":false,"isPointSeries":false,"scoringGroupName":"team_64697","headerLabel":"Points","displayNation":false,"showTotal":true,"showDeficitPoints":false,"useCustomFieldsAsFilter":false,"workouts":[{"id":65446,"key":"workout_65446","name":"Hoppin' and Poppin'!","logoPath":"","showDetails":true,"showPoints":true,"hasMissingScores":false,"caption":"Time","showRank":false,"headerLabel":"Points","scoresCount":2,"hasResultsOperations":false,"hasActiveResultsOperations":false,"resultsOperationsEndDate":null,"resultsOperationsNextStartDate":null},{"id":65575,"key":"workout_65575","name":"3-1-2? It's So Complex!","logoPath":"","showDetails":true,"showPoints":true,"hasMissingScores":false,"caption":"lb","showRank":false,"headerLabel":"Points","scoresCount":2,"hasResultsOperations":false,"hasActiveResultsOperations":false,"resultsOperationsEndDate":null,"resultsOperationsNextStartDate":null},{"id":65704,"key":"workout_65704","name":"Toss it, I'm Over It! (Row)","logoPath":"","showDetails":true,"showPoints":true,"hasMissingScores":false,"caption":"Calories","showRank":false,"headerLabel":"Points","scoresCount":2,"hasResultsOperations":false,"hasActiveResultsOperations":false,"resultsOperationsEndDate":null,"resultsOperationsNextStartDate":null},{"id":65833,"key":"workout_65833","name":"Toss it, I'm Over It! (Metcon)","logoPath":"","showDetails":true,"showPoints":true,"hasMissingScores":false,"caption":"Reps","showRank":false,"headerLabel":"Points","scoresCount":2,"hasResultsOperations":false,"hasActiveResultsOperations":false,"resultsOperationsEndDate":null,"resultsOperationsNextStartDate":null},{"id":65962,"key":"workout_65962","name":"Get on Up 'n Git Down","logoPath":"","showDetails":true,"showPoints":true,"hasMissingScores":true,"caption":"Time","showRank":false,"headerLabel":"Points","scoresCount":0,"hasResultsOperations":false,"hasActiveResultsOperations":false,"resultsOperationsEndDate":null,"resultsOperationsNextStartDate":null}],"athletes":[{"name":"The Dundies","avatarPath":null,"place":"1","totalPoints":"5","deficit":null,"totalWins":"3","topFiveFinishes":"4","subgroup":null,"subcategory":null,"events":null,"affiliate":"GSR FIT","ptcpID":"930221","rosterID":"486111","wd":false,"dnf":false,"pending":false,"isDisqualified":false,"submittedScores":4,"specialStatus":null,"nextScaled":false,"workoutScores":{"workout_65446":{"workoutId":65446,"points":"1","rank":"","res":"06:06","cssNames":"","nonOff":false,"caption":"Time","rankInnerValue":1,"hasHiddenResult":false,"hasVideo":false},"workout_65575":{"workoutId":65575,"points":"1","rank":"","res":"370","cssNames":"","nonOff":false,"caption":"Weight (lb)","rankInnerValue":1,"hasHiddenResult":false,"hasVideo":false},"workout_65704":{"workoutId":65704,"points":"2","rank":"","res":"185","cssNames":"","nonOff":false,"caption":"Calories","rankInnerValue":2,"hasHiddenResult":false,"hasVideo":false},"workout_65833":{"workoutId":65833,"points":"1","rank":"","res":"310","cssNames":"","nonOff":false,"caption":"Reps","rankInnerValue":1,"hasHiddenResult":false,"hasVideo":false},"workout_65962":{"workoutId":65962,"points":"","rank":"","res":"-","cssNames":"pending","nonOff":false,"caption":"Time","rankInnerValue":0,"hasHiddenResult":false,"hasVideo":false}},"countryName":"United States","countryCode":"USA","countryShortCode":"US","index":0,"ageGroup":null,"combinedTeamAge":60,"bibNumber":null,"participantAnswers":null,"infoOptionCustomFieldValue":null},{"name":"The Perfect Couplet","avatarPath":null,"place":"2","totalPoints":"7","deficit":null,"totalWins":"1","topFiveFinishes":"4","subgroup":null,"subcategory":null,"events":null,"affiliate":"GSR FIT","ptcpID":"934387","rosterID":"487879","wd":false,"dnf":false,"pending":false,"isDisqualified":false,"submittedScores":4,"specialStatus":null,"nextScaled":false,"workoutScores":{"workout_65446":{"workoutId":65446,"points":"2","rank":"","res":"07:21","cssNames":"","nonOff":false,"caption":"Time","rankInnerValue":2,"hasHiddenResult":false,"hasVideo":false},"workout_65575":{"workoutId":65575,"points":"2","rank":"","res":"355","cssNames":"","nonOff":false,"caption":"Weight (lb)","rankInnerValue":2,"hasHiddenResult":false,"hasVideo":false},"workout_65704":{"workoutId":65704,"points":"1","rank":"","res":"187","cssNames":"","nonOff":false,"caption":"Calories","rankInnerValue":1,"hasHiddenResult":false,"hasVideo":false},"workout_65833":{"workoutId":65833,"points":"2","rank":"","res":"285","cssNames":"","nonOff":false,"caption":"Reps","rankInnerValue":2,"hasHiddenResult":false,"hasVideo":false},"workout_65962":{"workoutId":65962,"points":"","rank":"","res":"-","cssNames":"pending","nonOff":false,"caption":"Time","rankInnerValue":0,"hasHiddenResult":false,"hasVideo":false}},"countryName":"United States","countryCode":"USA","countryShortCode":"US","index":1,"ageGroup":null,"combinedTeamAge":86,"bibNumber":null,"participantAnswers":null,"infoOptionCustomFieldValue":null}],"affiliateFilterValues":[],"countryFilterValues":[],"ageGroupsFilterValues":null,"subGroupFilterValues":null,"customFieldsFilterValues":null,"continentFilterValues":null,"regionFilterValues":null,"showGenderFilterValues":false,"hasAthletes":true}